minecraft_stores/Minecraft_Store.py
minecraft_stores/__init__.py
minecraft_stores/data.py
minecraft_stores-0.0.5.dist-info/METADATA
minecraft_stores-0.0.5.dist-info/WHEEL
minecraft_stores-0.0.5.dist-info/top_level.txt
minecraft_stores-0.0.5.dist-info/RECORD
