Metadata-Version: 2.1
Name: minecraft-stores
Version: 0.0.5
Summary: Python library for saving minecraft game data to disk.
Home-page: https://github.com/Nathan-Nesbitt/Minecraft_Store
Author: Carlos Rueda Carrasco, Kathryn Lecha, Nathan Nesbitt,Adrian Morillo Quiroga
License: UNKNOWN
Platform: UNKNOWN
Requires-Dist: pandas
Requires-Dist: wheel
Requires-Dist: nest-asyncio
Requires-Dist: pytest-asyncio
Requires-Dist: pytest
